dam4ml/__init__.py
dam4ml/client.py
dam4ml-1.0.0.dist-info/METADATA
dam4ml-1.0.0.dist-info/RECORD
dam4ml-1.0.0.dist-info/WHEEL
dam4ml-1.0.0.dist-info/top_level.txt
