Metadata-Version: 2.1
Name: dam4ml
Version: 1.0.0
Summary: Dam4ML client library
Home-page: https://github.com/numericube/dam4ml-client
Author: NumeriCube
Author-email: support@numericube.com
License: GPLv3
Platform: UNKNOWN
Classifier: Programming Language :: Python :: 3
Classifier: License :: OSI Approved :: GNU General Public License v3 (GPLv3)
